besser/__init__.py
besser/BUML/__init__.py
besser/BUML/metamodel/__init__.py
besser/BUML/metamodel/deployment/__init__.py
besser/BUML/metamodel/deployment/deployment.py
besser/BUML/metamodel/feature_model/__init__.py
besser/BUML/metamodel/feature_model/feature_model.py
besser/BUML/metamodel/gui/__init__.py
besser/BUML/metamodel/gui/binding.py
besser/BUML/metamodel/gui/dashboard.py
besser/BUML/metamodel/gui/events_actions.py
besser/BUML/metamodel/gui/graphical_ui.py
besser/BUML/metamodel/gui/style.py
besser/BUML/metamodel/nn/__init__.py
besser/BUML/metamodel/nn/neural_network.py
besser/BUML/metamodel/object/__init__.py
besser/BUML/metamodel/object/builder.py
besser/BUML/metamodel/object/object.py
besser/BUML/metamodel/ocl/__init__.py
besser/BUML/metamodel/ocl/ocl.py
besser/BUML/metamodel/project/__init__.py
besser/BUML/metamodel/project/project.py
besser/BUML/metamodel/quantum/__init__.py
besser/BUML/metamodel/quantum/quantum.py
besser/BUML/metamodel/state_machine/__init__.py
besser/BUML/metamodel/state_machine/agent.py
besser/BUML/metamodel/state_machine/state_machine.py
besser/BUML/metamodel/structural/__init__.py
besser/BUML/metamodel/structural/structural.py
besser/BUML/notations/__init__.py
besser/BUML/notations/deployment/__init__.py
besser/BUML/notations/deployment/buml_deployment.py
besser/BUML/notations/deployment/depl_to_buml_listener.py
besser/BUML/notations/deployment/deploymentLexer.py
besser/BUML/notations/deployment/deploymentListener.py
besser/BUML/notations/deployment/deploymentParser.py
besser/BUML/notations/mockup_to_buml/__init__.py
besser/BUML/notations/mockup_to_buml/config.py
besser/BUML/notations/mockup_to_buml/mockup_to_buml.py
besser/BUML/notations/mockup_to_buml/multiple_images.py
besser/BUML/notations/mockup_to_buml/one_page.py
besser/BUML/notations/mockup_to_buml/besser_integration/__init__.py
besser/BUML/notations/mockup_to_buml/besser_integration/refactor_gui_model.py
besser-6.2.0.dist-info/licenses/LICENSE.md
besser-6.2.0.dist-info/METADATA
besser-6.2.0.dist-info/WHEEL
besser-6.2.0.dist-info/top_level.txt
besser-6.2.0.dist-info/RECORD
