Metadata-Version: 2.4
Name: besser
Version: 6.2.0
Summary: BESSER
Author: Luxembourg Institute of Science and Technology
License: MIT
Project-URL: Documentation, https://besser.readthedocs.io/en/latest/
Project-URL: Source Code, https://github.com/BESSER-PEARL/BESSER
Project-URL: Bug Tracker, https://github.com/BESSER-PEARL/BESSER/issues
Keywords: uml,code generation,python
Requires-Python: >=3.10
License-File: LICENSE.md
Requires-Dist: Arpeggio>=2.0.2
Requires-Dist: colorama>=0.4.6
Requires-Dist: iniconfig>=2.0.0
Requires-Dist: packaging>=24.2
Requires-Dist: pluggy>=1.2.0
Requires-Dist: pytest>=7.4.0
Requires-Dist: python-multipart>=0.0.17
Requires-Dist: setuptools>=68.2.2
Requires-Dist: jinja2>=3.1.2
Requires-Dist: antlr4-python3-runtime>=4.13.1
Requires-Dist: requests>=2.31.0
Requires-Dist: pydantic>=2.6.3
Requires-Dist: uvicorn>=0.28.0
Requires-Dist: SQLAlchemy>=2.0.29
Requires-Dist: httpx>=0.27.0
Requires-Dist: docker>=7.1.0
Requires-Dist: Django>=5.1.5
Requires-Dist: oracledb>=3.4.1
Requires-Dist: psycopg2-binary>=2.9.10
Requires-Dist: pymysql>=1.1.1
Requires-Dist: pyodbc>=5.2.0
Provides-Extra: nn
Requires-Dist: pillow>=11.1.0; extra == "nn"
Requires-Dist: numpy>=2.2.4; extra == "nn"
Requires-Dist: torch>=2.6.0; extra == "nn"
Dynamic: license-file
